pyrpfiv/__init__.py
pyrpfiv/constants.py
pyrpfiv/crypto.py
pyrpfiv/exceptions.py
pyrpfiv/hashes.ini
pyrpfiv/parser.py
pyrpfiv-0.1.3.dist-info/LICENSE
pyrpfiv-0.1.3.dist-info/METADATA
pyrpfiv-0.1.3.dist-info/WHEEL
pyrpfiv-0.1.3.dist-info/RECORD
