Metadata-Version: 2.3
Name: pyrpfiv
Version: 0.1.3
Summary: A Python library for parsing and modifying RPF files for GTA IV.
License: MIT
Author: gmroder
Requires-Python: >=3.8,<4.0
Classifier: License :: OSI Approved :: MIT License
Classifier: Programming Language :: Python :: 3
Classifier: Programming Language :: Python :: 3.8
Classifier: Programming Language :: Python :: 3.9
Classifier: Programming Language :: Python :: 3.10
Classifier: Programming Language :: Python :: 3.11
Classifier: Programming Language :: Python :: 3.12
Classifier: Programming Language :: Python :: 3.13
Requires-Dist: pycryptodome (>=3.19.0,<4.0.0)
Project-URL: Homepage, https://github.com/gmroder/pyrpfiv
Project-URL: Repository, https://github.com/gmroder/pyrpfiv
